[
   {
      "meta": {
         "code": "ANCR",
         "label": {
            "en": "ANC Registration",
            "sw": "Sajilisha ANC"
         }
      },
      "fields": {
         "patient_name": {
            "labels": {
               "tiny": {
                 "en": "N",
                 "sw": "JINA"
               },
               "description": {
                 "en": "Name",
                 "sw": "Jina"
               },
               "short": {
                 "en": "Name",
                 "sw": "Jina"
               }
            },
            "position": 0,
            "type": "string",
            "length": [
               5,
               50
            ]
         },
         "last_menstrual_period": {
            "labels": {
               "tiny": {
                  "en": "LMP"
               },
               "description": {
                  "en": "Weeks since last menstrual period"
               },
               "short": {
                  "en": "Weeks since LMP"
               }
            },
            "position": 1,
            "type": "integer",
            "length": [
               1,
               2
            ],
            "range": [
               0,
               40
            ],
            "validations": {},
            "flags": {}
         },
         "age_in_years": {
            "labels": {
               "tiny": {
                  "en": "AGE",
                  "sw": "UMRI"
               },
               "description": {
                  "en": "Age In Years"
               },
               "short": {
                  "en": "Age In Years"
               }
            },
            "position": 2,
            "type": "integer",
            "length": [
               1,
               2
            ],
            "range": [
               1,
               40
            ],
            "validations": {},
            "flags": {}
         }
      },
      "use_sentinel": true
   },
   {
      "meta": {
         "code": "ANCV",
         "label": {
            "en": "ANC Visit",
            "sw": "Kudhibitisha ANC Klinik"
         }
      },
      "fields": {
         "patient_id": {
            "labels": {
               "tiny": {
                 "en": "ID"
               },
               "description": {
                 "en": "Patient Identifier"
               },
               "short": {
                 "en": "Patient ID"
               }
            },
            "position": 0,
            "flags": {
                "input_digits_only": true
            },
            "length": [
                5, 5
            ],
            "type": "string"
         }
      },
      "use_sentinel": true
   },
   {
      "meta": {
         "code": "IMMR",
         "label": {
            "en": "Immunization Registration",
            "sw": "Sajilisha Chanjo"
         }
      },
      "fields": {
         "patient_name": {
            "labels": {
               "tiny": {
                 "en": "child",
                 "sw": "mtoto"
               },
               "description": {
                 "en": "Child's Full Name",
                 "sw": "Jina"
               },
               "short": {
                 "en": "Child's Name",
                 "sw": "Jina"
               }
            },
            "position": 0,
            "type": "string",
            "length": [
               5,
               50
            ]
         },
         "mother_patient_id": {
            "labels": {
               "tiny": {
                  "en": "momid",
                  "sw": "mamaid"
               },
               "description": {
                  "en": "Mother's Patient Identifier"
               },
               "short": {
                  "en": "Mother's Patient ID"
               }
            },
            "position": 1,
            "flags": {
                "input_digits_only": true
            },
            "length": [
                5, 5
            ],
            "type": "string",
            "validations": {}
         },
         "weeks_since_birth": {
            "labels": {
               "tiny": {
                  "en": "dob",
                  "sw": "dob"
               },
               "description": {
                  "en": "Weeks since birth",
                  "sw": "wiki kutoka kuzaliwa"
               },
               "short": {
                  "en": "Weeks since birth",
                  "sw": "wiki kutoka kuzaliwa"
               }
            },
            "position": 2,
            "type": "integer",
            "length": [
               1,
               2
            ],
            "range": [
               0,
               52
            ],
            "validations": {},
            "flags": {}
         }
      },
      "use_sentinel": true
   },
   {
      "meta": {
         "code": "IMMV",
         "label": {
            "en": "Immunization Visit Confirmation",
            "sw": "Kudhibitisha klinik ya chanjo"
         }
      },
      "fields": {
         "patient_id": {
            "labels": {
               "tiny": {
                 "en": "ID"
               },
               "description": {
                 "en": "Patient Identifier"
               },
               "short": {
                 "en": "Patient ID"
               }
            },
            "position": 0,
            "flags": {
                "input_digits_only": true
            },
            "length": [
                5, 5
            ],
            "type": "string"
         }
      },
      "use_sentinel": true
   },
   {
      "meta": {
         "code": "OFF",
         "label": {
            "en": "Disable Notifications",
            "sw": "Toa"
         }
      },
      "fields": {
         "patient_id": {
            "labels": {
               "tiny": {
                 "en": "ID"
               },
               "description": {
                 "en": "Patient Identifier"
               },
               "short": {
                 "en": "Patient ID"
               }
            },
            "position": 0,
            "flags": {
                "input_digits_only": true
            },
            "length": [
                5, 5
            ],
            "type": "string"
         },
         "reason": {
            "labels": {
               "tiny": {
                 "en": "r",
                 "sw": "r"
               },
               "description": {
                 "en": "Reason",
                 "sw": "Reason"
               },
               "short": {
                 "en": "Reason",
                 "sw": "Reason"
               }
            },
            "position": 1,
            "length": [
                3, 100
            ],
            "type": "string"
         }
      },
      "use_sentinel": true
   },
   {
      "meta": {
         "code": "ON",
         "label": {
            "en": "Enable Notifications",
            "sw": "Rudisha"
         }
      },
      "fields": {
         "patient_id": {
            "labels": {
               "tiny": {
                 "en": "ID"
               },
               "description": {
                 "en": "Patient Identifier"
               },
               "short": {
                 "en": "Patient ID"
               }
            },
            "position": 0,
            "flags": {
                "input_digits_only": true
            },
            "length": [
                5, 5
            ],
            "type": "string"
         }
      },
      "use_sentinel": true
   },
   {
      "meta": {
         "code": "HATARI",
         "label": {
            "en": "Danger Signs",
            "sw": "Hatari"
         }
      },
      "fields": {
         "patient_name": {
            "labels": {
               "tiny": {
                 "en": "N",
                 "sw": "JINA"
               },
               "description": {
                 "en": "Full Name",
                 "sw": "Jina"
               },
               "short": {
                 "en": "Full Name",
                 "sw": "Jina"
               }
            },
            "position": 0,
            "type": "string",
            "length": [
               5,
               50
            ]
         }
      },
      "use_sentinel": true
   }
]
